pyhac/__init__.py
pyhac/controller/__init__.py
pyhac/controller/hac.py
pyhac/detector/__init__.py
pyhac/detector/action_detector.py
pyhac/detector/detector.py
pyhac/detector/gesture_detector.py
pyhac/model/__init__.py
pyhac/model/gcn.py
pyhac/model/graph.py
pyhac/model/hac_model.py
pyhac/module/__init__.py
pyhac/module/control.py
pyhac/module/module.py
pyhac/tracker/__init__.py
pyhac/tracker/holistic_tracker.py
pyhac/trained_model/__init__.py
pyhac/trained_model/gcn/actions/best_model.pth
pyhac/trained_model/gcn/down/best_model.pth
pyhac/trained_model/gcn/gather_town/best_model.pth
pyhac/trained_model/gcn/gestures/best_model.pth
pyhac/trained_model/gcn/mouse_control/best_model.pth
pyhac/trained_model/gcn/mouse_control_fast_slow/best_model.pth
pyhac/trained_model/gcn/pikachu/best_model.pth
pyhac-0.0.8.dist-info/LICENSE
pyhac-0.0.8.dist-info/METADATA
pyhac-0.0.8.dist-info/WHEEL
pyhac-0.0.8.dist-info/top_level.txt
pyhac-0.0.8.dist-info/RECORD
