Metadata-Version: 2.1
Name: pyhac
Version: 0.0.8
Summary: A human action controller running on different platforms
Home-page: https://github.com/dabit-lucas/hac
Author: JAQQ
Author-email: dabit-lucas@gmail.com, chen.jiunhan@gmail.com
License: Apache License 2.0
Keywords: human action controller
Platform: UNKNOWN
Requires-Dist: opencv-python
Requires-Dist: numpy
Requires-Dist: PyDirectInput (==1.0.4)
Requires-Dist: keyboard (==0.13.5)
Requires-Dist: torch (==1.9.0)
Requires-Dist: pandas (==1.2.5)
Requires-Dist: mouse (==0.7.1)
Requires-Dist: mediapipe (==0.8.6)
Requires-Dist: protobuf (==3.17.3)
Requires-Dist: PyAutoGUI (==0.9.53)
